<?xml version="1.0" encoding="UTF-8"?>
<!--
 ! (c) Copyright 2005-2013 JAXIO, http://www.jaxio.com
 ! Source code generated by Celerio, a Jaxio product
 ! Want to purchase Celerio ? email us at info@jaxio.com
 ! Follow us on twitter: @springfuse
 ! Documentation: http://www.jaxio.com/documentation/celerio/
 ! Template pack-backend-jpa:src/main/resources/localization/domain/domain.e.vm.xml
-->
<!DOCTYPE properties SYSTEM "http://java.sun.com/dtd/properties.dtd">
<properties>
	<comment>Domain resources for Town</comment>

	<entry key="town">Town</entry>
	<entry key="town_search">Search Town</entry>
	<entry key="town_create">Create Town</entry>
	<entry key="town_edit">Edit {0}</entry>
	<entry key="town_view">View {0}</entry>

	<!-- attributes -->
	<entry key="town_id">Id</entry>
	<entry key="town_department">Department</entry>
	<entry key="town_name">Name</entry>
	<entry key="town_nameReal">Name Real</entry>
	<entry key="town_postcode">Postcode</entry>
	<entry key="town_population">Population</entry>
	<entry key="town_area">Area</entry>
	<entry key="town_longitudeDeg">Longitude Deg</entry>
	<entry key="town_latitudeDeg">Latitude Deg</entry>
	<entry key="town_longitudeGrd">Longitude Grd</entry>
	<entry key="town_latitudeGrd">Latitude Grd</entry>
	<entry key="town_longitudeDms">Longitude Dms</entry>
	<entry key="town_latitudeDms">Latitude Dms</entry>
	<entry key="town_zmin">Zmin</entry>
	<entry key="town_zmax">Zmax</entry>

	<!-- uniques -->
	<entry key="town_composite_unique_constraint_error">A composite unique constraint has failed on Town</entry>
</properties>